{
	"grid_layout": [
		"..........",
		"..........",
		"..........",
		"..........",
		"..........",
		"..........",
		"..........",
		".########.",
		".#S....E#.",
		".########.",
		"..........",
		"..........",
		"..........",
		"..........",
		"..........",
		"..........",
		"..........",
		"..........",
		"..........",
		".........."
	],
	"number_sequence": [
		30,
		32,
		11,
		19,
		25,
		14,
		30,
		20,
		16,
		16,
		14,
		32,
		7,
		24,
		24,
		17,
		30,
		25,
		25,
		48,
		7,
		17,
		18,
		48,
		19,
		11,
		40,
		16,
		23,
		23,
		48,
		24,
		32,
		24,
		25,
		28,
		27,
		36,
		36,
		23,
		14,
		42,
		12,
		7,
		16,
		11,
		48,
		30,
		27,
		20,
		48,
		48,
		16,
		14,
		19,
		42,
		16,
		28,
		36,
		12,
		13,
		24,
		11,
		48,
		19,
		12,
		13,
		23,
		14,
		40,
		12,
		28,
		32,
		30,
		25,
		27,
		14,
		32,
		36,
		23,
		40,
		12,
		42,
		12,
		45,
		30,
		12,
		20,
		27,
		23,
		42,
		27,
		18,
		20,
		20,
		17,
		20,
		20,
		42,
		32,
		18,
		32,
		13,
		18,
		27,
		30,
		23,
		7,
		27,
		11,
		14,
		12,
		7,
		20,
		42,
		20,
		27,
		12,
		27,
		12,
		24,
		32,
		17,
		20,
		42,
		25,
		16,
		14,
		48,
		24,
		48,
		48,
		27,
		32,
		48,
		48,
		14,
		16,
		27,
		24,
		20,
		32
	],
	"starting_hp": 187,
	"tick_speed": 0.949152542372881,
	"ticks_between_spawns": 3,
	"tutorial_hints": []
}